{"filter":false,"title":"StateAH.json","tooltip":"/2206-Capstone-Appraised/client/components/Data/Graph/StateAH.json","undoManager":{"mark":-1,"position":-1,"stack":[[{"start":{"row":12,"column":24},"end":{"row":13,"column":87},"action":"insert","lines":["AllHouses.map(house => ","            Object.keys(house).filter(num => num != 'RegionName' && num != 'StateName')"],"id":2}]]},"ace":{"folds":[],"scrolltop":3376.5,"scrollleft":0,"selection":{"start":{"row":549,"column":23},"end":{"row":549,"column":23},"isBackwards":false},"options":{"guessTabSize":true,"useWrapMode":false,"wrapToView":true},"firstLineState":{"row":101,"state":"start","mode":"ace/mode/json"}},"hash":"99b564ad6ec190cda47af066bc2356d9323a9580","mime":"application/json","timestamp":1661696197197}